LICENSE
MANIFEST.in
README.rst
setup.py
paytm_oauth.egg-info/PKG-INFO
paytm_oauth.egg-info/SOURCES.txt
paytm_oauth.egg-info/dependency_links.txt
paytm_oauth.egg-info/requires.txt
paytm_oauth.egg-info/top_level.txt
paytmoauth/__init__.py
paytmoauth/context_processors.py
paytmoauth/urls.py
paytmoauth/views.py