Metadata-Version: 1.1
Name: paytm-oauth
Version: 0.1
Summary: Consumer for paytm oauth
Home-page: https://github.com/paytm/django-paytm-oauth
Author: Shrey Agarwal, Taranjeet Singh
Author-email: shrey.agarwal@paytm.com, reachtotj@gmail.com
License: MIT License
Platform: UNKNOWN
Classifier: Development Status :: 4 - Beta
Classifier: Environment :: Web Environment
Classifier: Framework :: Django :: 1.8
Classifier: Intended Audience :: Developers
Classifier: License :: OSI Approved :: MIT License
Classifier: Operating System :: OS Independent
Classifier: Programming Language :: Python
Classifier: Natural Language :: English
Classifier: Programming Language :: Python :: 3.4
Classifier: Framework :: Django :: 1.8
Classifier: Topic :: Internet :: WWW/HTTP
